<annotation>
	<folder>images</folder>
	<filename>VID_20180601_110656.mp4_frame_0864.jpg</filename>
	<path>/home/nikolas/Documents/NNTesting/datasets/strawberry/images/VID_20180601_110656.mp4_frame_0864.jpg</path>
	<source>
		<database>Unknown</database>
	</source>
	<size>
		<width>640</width>
		<height>360</height>
		<depth>3</depth>
	</size>
	<segmented>0</segmented>
	<object>
		<name>strawberry</name>
		<pose>Unspecified</pose>
		<truncated>0</truncated>
		<difficult>0</difficult>
		<bndbox>
			<xmin>123</xmin>
			<ymin>16</ymin>
			<xmax>141</xmax>
			<ymax>37</ymax>
		</bndbox>
	</object>
	<object>
		<name>strawberry</name>
		<pose>Unspecified</pose>
		<truncated>0</truncated>
		<difficult>0</difficult>
		<bndbox>
			<xmin>308</xmin>
			<ymin>244</ymin>
			<xmax>356</xmax>
			<ymax>286</ymax>
		</bndbox>
	</object>
	<object>
		<name>strawberry</name>
		<pose>Unspecified</pose>
		<truncated>0</truncated>
		<difficult>0</difficult>
		<bndbox>
			<xmin>591</xmin>
			<ymin>239</ymin>
			<xmax>629</xmax>
			<ymax>269</ymax>
		</bndbox>
	</object>
	<object>
		<name>strawberry</name>
		<pose>Unspecified</pose>
		<truncated>0</truncated>
		<difficult>0</difficult>
		<bndbox>
			<xmin>611</xmin>
			<ymin>278</ymin>
			<xmax>638</xmax>
			<ymax>312</ymax>
		</bndbox>
	</object>
</annotation>
