<annotation>
	<folder>images</folder>
	<filename>VID_20180601_110656.mp4_frame_1586.jpg</filename>
	<path>/home/nikolas/Documents/NNTesting/datasets/strawberry/images/VID_20180601_110656.mp4_frame_1586.jpg</path>
	<source>
		<database>Unknown</database>
	</source>
	<size>
		<width>640</width>
		<height>360</height>
		<depth>3</depth>
	</size>
	<segmented>0</segmented>
	<object>
		<name>strawberry</name>
		<pose>Unspecified</pose>
		<truncated>0</truncated>
		<difficult>0</difficult>
		<bndbox>
			<xmin>601</xmin>
			<ymin>309</ymin>
			<xmax>636</xmax>
			<ymax>346</ymax>
		</bndbox>
	</object>
	<object>
		<name>strawberry</name>
		<pose>Unspecified</pose>
		<truncated>0</truncated>
		<difficult>0</difficult>
		<bndbox>
			<xmin>547</xmin>
			<ymin>282</ymin>
			<xmax>576</xmax>
			<ymax>310</ymax>
		</bndbox>
	</object>
	<object>
		<name>strawberry</name>
		<pose>Unspecified</pose>
		<truncated>0</truncated>
		<difficult>0</difficult>
		<bndbox>
			<xmin>435</xmin>
			<ymin>97</ymin>
			<xmax>460</xmax>
			<ymax>129</ymax>
		</bndbox>
	</object>
	<object>
		<name>strawberry</name>
		<pose>Unspecified</pose>
		<truncated>0</truncated>
		<difficult>0</difficult>
		<bndbox>
			<xmin>271</xmin>
			<ymin>36</ymin>
			<xmax>299</xmax>
			<ymax>73</ymax>
		</bndbox>
	</object>
</annotation>
