<annotation>
	<folder>images</folder>
	<filename>VID_20180601_110656.mp4_frame_3349.jpg</filename>
	<path>/home/nikolas/Documents/NNTesting/datasets/strawberry/images/VID_20180601_110656.mp4_frame_3349.jpg</path>
	<source>
		<database>Unknown</database>
	</source>
	<size>
		<width>640</width>
		<height>360</height>
		<depth>3</depth>
	</size>
	<segmented>0</segmented>
	<object>
		<name>strawberry</name>
		<pose>Unspecified</pose>
		<truncated>0</truncated>
		<difficult>0</difficult>
		<bndbox>
			<xmin>588</xmin>
			<ymin>291</ymin>
			<xmax>620</xmax>
			<ymax>318</ymax>
		</bndbox>
	</object>
	<object>
		<name>strawberry</name>
		<pose>Unspecified</pose>
		<truncated>0</truncated>
		<difficult>0</difficult>
		<bndbox>
			<xmin>316</xmin>
			<ymin>204</ymin>
			<xmax>345</xmax>
			<ymax>235</ymax>
		</bndbox>
	</object>
	<object>
		<name>strawberry</name>
		<pose>Unspecified</pose>
		<truncated>0</truncated>
		<difficult>0</difficult>
		<bndbox>
			<xmin>118</xmin>
			<ymin>218</ymin>
			<xmax>160</xmax>
			<ymax>255</ymax>
		</bndbox>
	</object>
	<object>
		<name>strawberry</name>
		<pose>Unspecified</pose>
		<truncated>0</truncated>
		<difficult>0</difficult>
		<bndbox>
			<xmin>100</xmin>
			<ymin>241</ymin>
			<xmax>146</xmax>
			<ymax>279</ymax>
		</bndbox>
	</object>
	<object>
		<name>strawberry</name>
		<pose>Unspecified</pose>
		<truncated>0</truncated>
		<difficult>0</difficult>
		<bndbox>
			<xmin>106</xmin>
			<ymin>291</ymin>
			<xmax>141</xmax>
			<ymax>322</ymax>
		</bndbox>
	</object>
	<object>
		<name>strawberry</name>
		<pose>Unspecified</pose>
		<truncated>1</truncated>
		<difficult>0</difficult>
		<bndbox>
			<xmin>1</xmin>
			<ymin>301</ymin>
			<xmax>24</xmax>
			<ymax>334</ymax>
		</bndbox>
	</object>
	<object>
		<name>strawberry</name>
		<pose>Unspecified</pose>
		<truncated>0</truncated>
		<difficult>0</difficult>
		<bndbox>
			<xmin>42</xmin>
			<ymin>178</ymin>
			<xmax>61</xmax>
			<ymax>207</ymax>
		</bndbox>
	</object>
	<object>
		<name>strawberry</name>
		<pose>Unspecified</pose>
		<truncated>0</truncated>
		<difficult>0</difficult>
		<bndbox>
			<xmin>216</xmin>
			<ymin>185</ymin>
			<xmax>246</xmax>
			<ymax>210</ymax>
		</bndbox>
	</object>
</annotation>
