<annotation>
	<folder>images</folder>
	<filename>VID_20180601_110656.mp4_frame_3472.jpg</filename>
	<path>/home/nikolas/Documents/NNTesting/datasets/strawberry/images/VID_20180601_110656.mp4_frame_3472.jpg</path>
	<source>
		<database>Unknown</database>
	</source>
	<size>
		<width>640</width>
		<height>360</height>
		<depth>3</depth>
	</size>
	<segmented>0</segmented>
	<object>
		<name>strawberry</name>
		<pose>Unspecified</pose>
		<truncated>0</truncated>
		<difficult>0</difficult>
		<bndbox>
			<xmin>292</xmin>
			<ymin>215</ymin>
			<xmax>317</xmax>
			<ymax>241</ymax>
		</bndbox>
	</object>
	<object>
		<name>strawberry</name>
		<pose>Unspecified</pose>
		<truncated>0</truncated>
		<difficult>0</difficult>
		<bndbox>
			<xmin>289</xmin>
			<ymin>239</ymin>
			<xmax>314</xmax>
			<ymax>272</ymax>
		</bndbox>
	</object>
	<object>
		<name>strawberry</name>
		<pose>Unspecified</pose>
		<truncated>0</truncated>
		<difficult>0</difficult>
		<bndbox>
			<xmin>327</xmin>
			<ymin>263</ymin>
			<xmax>354</xmax>
			<ymax>297</ymax>
		</bndbox>
	</object>
	<object>
		<name>strawberry</name>
		<pose>Unspecified</pose>
		<truncated>0</truncated>
		<difficult>0</difficult>
		<bndbox>
			<xmin>393</xmin>
			<ymin>202</ymin>
			<xmax>427</xmax>
			<ymax>236</ymax>
		</bndbox>
	</object>
	<object>
		<name>strawberry</name>
		<pose>Unspecified</pose>
		<truncated>0</truncated>
		<difficult>0</difficult>
		<bndbox>
			<xmin>461</xmin>
			<ymin>282</ymin>
			<xmax>504</xmax>
			<ymax>326</ymax>
		</bndbox>
	</object>
	<object>
		<name>strawberry</name>
		<pose>Unspecified</pose>
		<truncated>0</truncated>
		<difficult>0</difficult>
		<bndbox>
			<xmin>604</xmin>
			<ymin>193</ymin>
			<xmax>633</xmax>
			<ymax>227</ymax>
		</bndbox>
	</object>
</annotation>
