<annotation>
	<folder>images</folder>
	<filename>VID_20180601_110656.mp4_frame_3978.jpg</filename>
	<path>/home/nikolas/Documents/NNTesting/datasets/strawberry/images/VID_20180601_110656.mp4_frame_3978.jpg</path>
	<source>
		<database>Unknown</database>
	</source>
	<size>
		<width>640</width>
		<height>360</height>
		<depth>3</depth>
	</size>
	<segmented>0</segmented>
	<object>
		<name>strawberry</name>
		<pose>Unspecified</pose>
		<truncated>0</truncated>
		<difficult>0</difficult>
		<bndbox>
			<xmin>2</xmin>
			<ymin>61</ymin>
			<xmax>27</xmax>
			<ymax>101</ymax>
		</bndbox>
	</object>
	<object>
		<name>strawberry</name>
		<pose>Unspecified</pose>
		<truncated>0</truncated>
		<difficult>0</difficult>
		<bndbox>
			<xmin>26</xmin>
			<ymin>6</ymin>
			<xmax>67</xmax>
			<ymax>31</ymax>
		</bndbox>
	</object>
	<object>
		<name>strawberry</name>
		<pose>Unspecified</pose>
		<truncated>1</truncated>
		<difficult>0</difficult>
		<bndbox>
			<xmin>1</xmin>
			<ymin>210</ymin>
			<xmax>15</xmax>
			<ymax>240</ymax>
		</bndbox>
	</object>
	<object>
		<name>strawberry</name>
		<pose>Unspecified</pose>
		<truncated>0</truncated>
		<difficult>0</difficult>
		<bndbox>
			<xmin>306</xmin>
			<ymin>171</ymin>
			<xmax>335</xmax>
			<ymax>201</ymax>
		</bndbox>
	</object>
	<object>
		<name>strawberry</name>
		<pose>Unspecified</pose>
		<truncated>0</truncated>
		<difficult>0</difficult>
		<bndbox>
			<xmin>389</xmin>
			<ymin>182</ymin>
			<xmax>421</xmax>
			<ymax>215</ymax>
		</bndbox>
	</object>
	<object>
		<name>strawberry</name>
		<pose>Unspecified</pose>
		<truncated>0</truncated>
		<difficult>0</difficult>
		<bndbox>
			<xmin>468</xmin>
			<ymin>169</ymin>
			<xmax>497</xmax>
			<ymax>201</ymax>
		</bndbox>
	</object>
	<object>
		<name>strawberry</name>
		<pose>Unspecified</pose>
		<truncated>0</truncated>
		<difficult>0</difficult>
		<bndbox>
			<xmin>525</xmin>
			<ymin>165</ymin>
			<xmax>557</xmax>
			<ymax>202</ymax>
		</bndbox>
	</object>
	<object>
		<name>strawberry</name>
		<pose>Unspecified</pose>
		<truncated>0</truncated>
		<difficult>0</difficult>
		<bndbox>
			<xmin>545</xmin>
			<ymin>190</ymin>
			<xmax>573</xmax>
			<ymax>224</ymax>
		</bndbox>
	</object>
	<object>
		<name>strawberry</name>
		<pose>Unspecified</pose>
		<truncated>0</truncated>
		<difficult>0</difficult>
		<bndbox>
			<xmin>541</xmin>
			<ymin>302</ymin>
			<xmax>579</xmax>
			<ymax>346</ymax>
		</bndbox>
	</object>
</annotation>
