<annotation>
	<folder>images</folder>
	<filename>VID_20180601_110926.mp4_frame_0178.jpg</filename>
	<path>C:\Users\nikol\DeepLearning\images\VID_20180601_110926.mp4_frame_0178.jpg</path>
	<source>
		<database>Unknown</database>
	</source>
	<size>
		<width>640</width>
		<height>360</height>
		<depth>3</depth>
	</size>
	<segmented>0</segmented>
	<object>
		<name>strawberry</name>
		<pose>Unspecified</pose>
		<truncated>0</truncated>
		<difficult>0</difficult>
		<bndbox>
			<xmin>531</xmin>
			<ymin>232</ymin>
			<xmax>555</xmax>
			<ymax>254</ymax>
		</bndbox>
	</object>
	<object>
		<name>strawberry</name>
		<pose>Unspecified</pose>
		<truncated>0</truncated>
		<difficult>0</difficult>
		<bndbox>
			<xmin>158</xmin>
			<ymin>296</ymin>
			<xmax>196</xmax>
			<ymax>337</ymax>
		</bndbox>
	</object>
	<object>
		<name>strawberry</name>
		<pose>Unspecified</pose>
		<truncated>0</truncated>
		<difficult>0</difficult>
		<bndbox>
			<xmin>227</xmin>
			<ymin>133</ymin>
			<xmax>259</xmax>
			<ymax>166</ymax>
		</bndbox>
	</object>
	<object>
		<name>strawberry</name>
		<pose>Unspecified</pose>
		<truncated>0</truncated>
		<difficult>0</difficult>
		<bndbox>
			<xmin>195</xmin>
			<ymin>81</ymin>
			<xmax>219</xmax>
			<ymax>104</ymax>
		</bndbox>
	</object>
</annotation>
